wgpu_shadertoy/__init__.py
wgpu_shadertoy/api.py
wgpu_shadertoy/cli.py
wgpu_shadertoy/inputs.py
wgpu_shadertoy/passes.py
wgpu_shadertoy/shadertoy.py
wgpu_shadertoy-0.2.0.dist-info/licenses/LICENSE
wgpu_shadertoy-0.2.0.dist-info/METADATA
wgpu_shadertoy-0.2.0.dist-info/WHEEL
wgpu_shadertoy-0.2.0.dist-info/entry_points.txt
wgpu_shadertoy-0.2.0.dist-info/top_level.txt
wgpu_shadertoy-0.2.0.dist-info/RECORD
