Metadata-Version: 2.4
Name: wgpu-shadertoy
Version: 0.2.0
Summary: Shadertoy implementation based on wgpu-py
Author-email: Jan Kels <Jan.Kels@hhu.de>
License: BSD 2-Clause License
Project-URL: Repository, https://github.com/pygfx/shadertoy
Requires-Python: >=3.9.0
License-File: LICENSE
Requires-Dist: wgpu>=0.21.1
Requires-Dist: requests
Requires-Dist: numpy
Requires-Dist: Pillow
Provides-Extra: dev
Requires-Dist: numpy; extra == "dev"
Requires-Dist: pytest; extra == "dev"
Requires-Dist: ruff; extra == "dev"
Requires-Dist: imageio; extra == "dev"
Requires-Dist: wheel; extra == "dev"
Requires-Dist: setuptools; extra == "dev"
Requires-Dist: twine; extra == "dev"
Requires-Dist: glfw; extra == "dev"
Dynamic: license-file
